boto3_oversize/__init__.py
boto3_oversize/oversize.py
boto3_oversize/py.typed
boto3_oversize/tests/__init__.py
boto3_oversize/tests/test_functional.py
boto3_oversize/tests/test_unit.py
boto3_oversize-0.1.4.dist-info/METADATA
boto3_oversize-0.1.4.dist-info/WHEEL
boto3_oversize-0.1.4.dist-info/RECORD
