Metadata-Version: 2.3
Name: boto3-oversize
Version: 0.1.4
Summary: Transparently stores oversize SNS messages in S3 and retrieves them when receiving messages using SQS.
License: MIT
Author: roberthl
Author-email: roberthl@users.noreply.github.com
Requires-Python: >=3.9,<4.0
Classifier: Intended Audience :: Developers
Classifier: License :: OSI Approved :: MIT License
Classifier: Operating System :: OS Independent
Classifier: Programming Language :: Python :: 3
Classifier: Programming Language :: Python :: 3.9
Classifier: Programming Language :: Python :: 3.10
Classifier: Programming Language :: Python :: 3.11
Classifier: Programming Language :: Python :: 3.12
Classifier: Programming Language :: Python :: 3.13
Requires-Dist: boto3 (>=1.20.30)
Requires-Dist: boto3-stubs[s3,sns,sqs] (>=1.20.30)
